odoo10_addon_base_vat_sanitized-10.0.1.0.0-py2.7-nspkg.pth
odoo10_addon_base_vat_sanitized-10.0.1.0.0.dist-info/top_level.txt
odoo10_addon_base_vat_sanitized-10.0.1.0.0.dist-info/WHEEL
odoo10_addon_base_vat_sanitized-10.0.1.0.0.dist-info/RECORD
odoo10_addon_base_vat_sanitized-10.0.1.0.0.dist-info/metadata.json
odoo10_addon_base_vat_sanitized-10.0.1.0.0.dist-info/DESCRIPTION.rst
odoo10_addon_base_vat_sanitized-10.0.1.0.0.dist-info/METADATA
odoo10_addon_base_vat_sanitized-10.0.1.0.0.dist-info/namespace_packages.txt
odoo/addons/base_vat_sanitized/__manifest__.py
odoo/addons/base_vat_sanitized/__init__.py
odoo/addons/base_vat_sanitized/README.rst
odoo/addons/base_vat_sanitized/models/res_partner.py
odoo/addons/base_vat_sanitized/models/__init__.py
odoo/addons/base_vat_sanitized/i18n/es.po
odoo/addons/base_vat_sanitized/i18n/sl.po
odoo/addons/base_vat_sanitized/tests/test_vat.py
odoo/addons/base_vat_sanitized/tests/__init__.py
